{
  "schema_version": 1,
  "framework": "megatron_distributed",
  "gpu_arch": "mi325",
  "enforce_thresholds": true,
  "config": {
    "hf_token_file": "/home/{user-id}/.hf_token",
    "log_dir": "/home/{user-id}/LOGS/megatron",
    "scripts_dir": "/home/{user-id}/SCRIPTS/megatron",
    "data_cache_dir": "/home/{user-id}/cache",
    "rocm_dir": "",
    "megatron_root": "/workspace/Megatron-LM",
    "training_iterations": "10",
    "nnodes": "<changeme>",
    "master_address": "<changeme>",
    "nic_type": "<changeme>",
    "nccl_ib_hca_list": "<changeme>",
    "nccl_ib_hca": "<changeme>",
    "nccl_socket_ifname": "<changeme>",
    "gloo_socket_ifname": "<changeme>",
    "hca_id_pattern": "bnxt_|rocep",
    "nccl_ib_gid_index": "3",
    "nccl_debug": "ERROR",
    "verify_network_errors": "True"
  },
  "model_params": {
    "model_name": "llama3_3_70b",
    "tokenizer_model": "meta-llama/Llama-3.3-70B-Instruct",
    "model_size": "70",
    "sequence_length": "8192",
    "recompute": "1",
    "fsdp": "1",
    "tensor_parallelism": "8",
    "pipeline_parallelism": "1",
    "precision": "TE_FP8"
  },
  "container": {
    "lifetime": "per_run",
    "name": "megatron_llama3_3_70b_distributed",
    "image": "<changeme>",
    "runtime": {
      "name": "docker",
      "args": {
        "network": "host",
        "ipc": "host",
        "privileged": true,
        "volumes": [
          "/home/{user-id}:/home/{user-id}",
          "/dev/infiniband:/dev/infiniband"
        ],
        "devices": [
          "/dev/kfd",
          "/dev/dri",
          "/dev/infiniband/rdma_cm"
        ]
      }
    }
  },
  "sweep": {
    "combinations": {
      "llama3_3_70b-mi325-bs64-mbs1-fp8": {
        "name": "llama3_3_70b_mbs1_gbs64_TE_FP8",
        "global_batch_size": "64",
        "micro_batch_size": "1",
        "precision": "TE_FP8",
        "result_dict": {
          "throughput_per_gpu": "100",
          "elapsed_time_per_iteration": "500",
          "tokens_per_gpu": "1000",
          "mem_usage": "0"
        }
      },
      "llama3_3_70b-mi325-bs64-mbs1-bf16": {
        "name": "llama3_3_70b_mbs1_gbs64_TE_BF16",
        "global_batch_size": "64",
        "micro_batch_size": "1",
        "precision": "TE_BF16",
        "result_dict": {
          "throughput_per_gpu": "100",
          "elapsed_time_per_iteration": "500",
          "tokens_per_gpu": "1000",
          "mem_usage": "0"
        }
      }
    },
    "runs": [
      "llama3_3_70b-mi325-bs64-mbs1-fp8",
      "llama3_3_70b-mi325-bs64-mbs1-bf16"
    ]
  }
}
